odoo/addons/account_payment_mode/README.rst
odoo/addons/account_payment_mode/__init__.py
odoo/addons/account_payment_mode/__manifest__.py
odoo/addons/account_payment_mode/demo/payment_demo.xml
odoo/addons/account_payment_mode/i18n/account_payment_mode.pot
odoo/addons/account_payment_mode/i18n/am.po
odoo/addons/account_payment_mode/i18n/ca.po
odoo/addons/account_payment_mode/i18n/da_DK.po
odoo/addons/account_payment_mode/i18n/de.po
odoo/addons/account_payment_mode/i18n/el_GR.po
odoo/addons/account_payment_mode/i18n/es.po
odoo/addons/account_payment_mode/i18n/es_AR.po
odoo/addons/account_payment_mode/i18n/es_ES.po
odoo/addons/account_payment_mode/i18n/fi.po
odoo/addons/account_payment_mode/i18n/fr.po
odoo/addons/account_payment_mode/i18n/gl.po
odoo/addons/account_payment_mode/i18n/hr.po
odoo/addons/account_payment_mode/i18n/it.po
odoo/addons/account_payment_mode/i18n/nb_NO.po
odoo/addons/account_payment_mode/i18n/nl.po
odoo/addons/account_payment_mode/i18n/pt.po
odoo/addons/account_payment_mode/i18n/pt_BR.po
odoo/addons/account_payment_mode/i18n/pt_PT.po
odoo/addons/account_payment_mode/i18n/sl.po
odoo/addons/account_payment_mode/i18n/tr.po
odoo/addons/account_payment_mode/i18n/zh_CN.po
odoo/addons/account_payment_mode/migrations/13.0.1.0.0/noupdate_changes.xml
odoo/addons/account_payment_mode/migrations/13.0.1.0.0/post-migration.py
odoo/addons/account_payment_mode/models/__init__.py
odoo/addons/account_payment_mode/models/account_journal.py
odoo/addons/account_payment_mode/models/account_payment_method.py
odoo/addons/account_payment_mode/models/account_payment_mode.py
odoo/addons/account_payment_mode/readme/CONFIGURE.rst
odoo/addons/account_payment_mode/readme/CONTRIBUTORS.rst
odoo/addons/account_payment_mode/readme/DESCRIPTION.rst
odoo/addons/account_payment_mode/readme/USAGE.rst
odoo/addons/account_payment_mode/security/account_payment_mode.xml
odoo/addons/account_payment_mode/security/ir.model.access.csv
odoo13_addon_account_payment_mode-13.0.1.2.1.dist-info/METADATA
odoo13_addon_account_payment_mode-13.0.1.2.1.dist-info/WHEEL
odoo13_addon_account_payment_mode-13.0.1.2.1.dist-info/top_level.txt
odoo13_addon_account_payment_mode-13.0.1.2.1.dist-info/RECORD
